Quartz/__init__.py
Quartz/CoreGraphics/__init__.py
Quartz/CoreGraphics/_callbacks.cpython-314-darwin.so
Quartz/CoreGraphics/_contextmanager.py
Quartz/CoreGraphics/_coregraphics.cpython-314-darwin.so
Quartz/CoreGraphics/_doubleindirect.cpython-314-darwin.so
Quartz/CoreGraphics/_inlines.cpython-314-darwin.so
Quartz/CoreGraphics/_metadata.py
Quartz/CoreGraphics/_sortandmap.cpython-314-darwin.so
Quartz/CoreVideo/_CVPixelBuffer.cpython-314-darwin.so
Quartz/CoreVideo/__init__.py
Quartz/CoreVideo/_metadata.py
Quartz/ImageIO/PyObjCOverrides.bridgesupport
Quartz/ImageIO/__init__.py
Quartz/ImageIO/_metadata.py
Quartz/ImageKit/__init__.py
Quartz/ImageKit/_imagekit.cpython-314-darwin.so
Quartz/ImageKit/_metadata.py
Quartz/PDFKit/_PDFKit.cpython-314-darwin.so
Quartz/PDFKit/__init__.py
Quartz/PDFKit/_metadata.py
Quartz/QuartzComposer/__init__.py
Quartz/QuartzComposer/_metadata.py
Quartz/QuartzCore/__init__.py
Quartz/QuartzCore/_metadata.py
Quartz/QuartzCore/_quartzcore.cpython-314-darwin.so
Quartz/QuartzFilters/__init__.py
Quartz/QuartzFilters/_metadata.py
Quartz/QuickLookUI/_QuickLookUI.cpython-314-darwin.so
Quartz/QuickLookUI/__init__.py
Quartz/QuickLookUI/_metadata.py
pyobjc_framework_quartz-12.1.dist-info/licenses/LICENSE.txt
pyobjc_framework_quartz-12.1.dist-info/METADATA
pyobjc_framework_quartz-12.1.dist-info/WHEEL
pyobjc_framework_quartz-12.1.dist-info/pyobjc-build-info.txt
pyobjc_framework_quartz-12.1.dist-info/top_level.txt
pyobjc_framework_quartz-12.1.dist-info/RECORD
